ostk/__init__.py
ostk/simulation/OpenSpaceToolkitSimulationPy.cpython-313-aarch64-linux-gnu.so
ostk/simulation/__init__.py
ostk/simulation/__init__.pyi
ostk/simulation/component.pyi
ostk/simulation/libopen-space-toolkit-simulation.so.4
ostk/simulation/test/__init__.py
ostk/simulation/test/test_import.py
ostk/simulation/test/test_satellite.py
ostk/simulation/test/test_simulator.py
open_space_toolkit_simulation-4.1.1.dist-info/METADATA
open_space_toolkit_simulation-4.1.1.dist-info/WHEEL
open_space_toolkit_simulation-4.1.1.dist-info/top_level.txt
open_space_toolkit_simulation-4.1.1.dist-info/zip-safe
open_space_toolkit_simulation-4.1.1.dist-info/RECORD
